flask_request_id_header/__init__.py
flask_request_id_header/middleware/__init__.py
flask_request_id_header-0.1.1.dist-info/LICENSE.md
flask_request_id_header-0.1.1.dist-info/METADATA
flask_request_id_header-0.1.1.dist-info/WHEEL
flask_request_id_header-0.1.1.dist-info/top_level.txt
flask_request_id_header-0.1.1.dist-info/RECORD
