Metadata-Version: 2.1
Name: flask-request-id-header
Version: 0.1.1
Summary: Python Flask middleware to ensure all requests have a request ID header
Home-page: https://github.com/antarctica/flask-request-id-header
Author: British Antarctic Survey
Author-email: webapps@bas.ac.uk
License: Open Government Licence v3.0
Platform: UNKNOWN
Classifier: Programming Language :: Python :: 3
Classifier: Framework :: Flask
Classifier: Development Status :: 5 - Production/Stable
Classifier: License :: Other/Proprietary License
Classifier: Operating System :: OS Independent
Classifier: Intended Audience :: Developers
